LICENSE
README.md
pyproject.toml
setup.cfg
setup.py
django_alegriadb/__init__.py
django_alegriadb/admin.py
django_alegriadb/apps.py
django_alegriadb/models.py
django_alegriadb/tests.py
django_alegriadb/views.py
django_alegriadb.egg-info/PKG-INFO
django_alegriadb.egg-info/SOURCES.txt
django_alegriadb.egg-info/dependency_links.txt
django_alegriadb.egg-info/requires.txt
django_alegriadb.egg-info/top_level.txt
django_alegriadb/migrations/0001_initial.py
django_alegriadb/migrations/__init__.py
django_alegriadb/utils/__init__.py
django_alegriadb/utils/alegria_admin_funcitons.py