Metadata-Version: 2.1
Name: django-alegriadb
Version: 0.0.12
Summary: Just A test
Home-page: https://www.example.com/
Author: HappyBoyJF
Author-email: joseprogfisica@gmail.com.br
License: MIT License
Classifier: Environment :: Web Environment
Classifier: Framework :: Django
Classifier: Intended Audience :: Developers
Classifier: License :: OSI Approved :: BSD License
Classifier: Operating System :: OS Independent
Classifier: Programming Language :: Python
Classifier: Programming Language :: Python :: 3
Classifier: Topic :: Internet :: WWW/HTTP
Classifier: Topic :: Internet :: WWW/HTTP :: Dynamic Content
Requires-Python: >=3.5
License-File: LICENSE
Requires-Dist: Django>=3.0.5
